CHANGES.txt
CONTRIBUTORS.txt
MANIFEST.in
README.rst
setup.py
collective/__init__.py
collective.pfg.signup.egg-info/PKG-INFO
collective.pfg.signup.egg-info/SOURCES.txt
collective.pfg.signup.egg-info/dependency_links.txt
collective.pfg.signup.egg-info/entry_points.txt
collective.pfg.signup.egg-info/namespace_packages.txt
collective.pfg.signup.egg-info/not-zip-safe
collective.pfg.signup.egg-info/requires.txt
collective.pfg.signup.egg-info/top_level.txt
collective/pfg/__init__.py
collective/pfg/signup/__init__.py
collective/pfg/signup/adapter.py
collective/pfg/signup/config.py
collective/pfg/signup/configure.zcml
collective/pfg/signup/interfaces.py
collective/pfg/signup/patches.py
collective/pfg/signup/testing.py
collective/pfg/signup/views.py
collective/pfg/signup/profiles/default/factorytool.xml
collective/pfg/signup/profiles/default/metadata.xml
collective/pfg/signup/profiles/default/rolemap.xml
collective/pfg/signup/profiles/default/types.xml
collective/pfg/signup/profiles/default/workflows.xml
collective/pfg/signup/profiles/default/types/FormFolder.xml
collective/pfg/signup/profiles/default/types/SignUpAdapter.xml
collective/pfg/signup/templates/user_approver_view.pt
collective/pfg/signup/templates/user_edit_view.pt
collective/pfg/signup/templates/user_profile_view.pt
collective/pfg/signup/templates/user_search_view.pt
collective/pfg/signup/tests/__init__.py
collective/pfg/signup/tests/testDocTests.py
collective/pfg/signup/tests/test_adapter.py
docs/LICENSE.GPL
docs/LICENSE.txt