Metadata-Version: 2.1
Name: collective.pfg.signup
Version: 1.6.1
Summary: A PloneFormGen adapter that saves signup form
Home-page: http://github.com/collective/collective.pfg.signup
Author: Pretaweb
Author-email: mailto:support@pretaweb.com
License: GPL
Keywords: plone ploneformgen form signup users
Platform: UNKNOWN
Classifier: Framework :: Plone
Classifier: Framework :: Plone :: 5.0
Classifier: Framework :: Plone :: 5.1
Classifier: Framework :: Plone :: 5.2
Classifier: Framework :: Plone :: Addon
Classifier: Programming Language :: Python
Classifier: Programming Language :: Python :: 2.7
Classifier: Programming Language :: Python :: 3.6
Classifier: Programming Language :: Python :: 3.7
Classifier: Topic :: Software Development :: Libraries :: Python Modules
Classifier: Development Status :: 4 - Beta
Classifier: License :: OSI Approved :: GNU General Public License (GPL)
Classifier: Operating System :: OS Independent
Provides-Extra: test
